hclust2.py
hclust2-0.99.dist-info/METADATA
hclust2-0.99.dist-info/WHEEL
hclust2-0.99.dist-info/entry_points.txt
hclust2-0.99.dist-info/top_level.txt
hclust2-0.99.dist-info/RECORD
