Metadata-Version: 2.1
Name: hclust2
Version: 0.99
Summary: Hclust2 is a handy tool for plotting heat-maps with several useful options to produce high quality figures that can be used in publication
Home-page: http://github.com/SegataLab/hclust2/
Author: Francesco Asnicar
Author-email: f.asnicar@unitn.it
License: UNKNOWN
Platform: UNKNOWN
Requires-Dist: numpy
Requires-Dist: scipy
Requires-Dist: pandas
Requires-Dist: matplotlib
